Metadata-Version: 1.1
Name: bibliothequetoulouse
Version: 0.1.6
Summary: Package pour interroger le catalogue des bibliothèques de Toulouse
Home-page: https://github.com/thibdct/bibliotheque-toulouse-python
Author: Thibault Ducret
Author-email: thibault.ducret@gmail.com
License: MIT
Download-URL: https://github.com/thibdct/bibliotheque-toulouse-python/tarball/0.1.6
Keywords: api,bibliothèque,toulouse
Platform: Posix; MacOS X
Classifier: Programming Language :: Python :: 2.7
